ribotish/__init__.py
ribotish/run/__init__.py
ribotish/run/predict.py
ribotish/run/quality.py
ribotish/run/tisdiff.py
ribotish/run/transplot.py
ribotish/zbio/__init__.py
ribotish/zbio/bam.py
ribotish/zbio/bed.py
ribotish/zbio/exp.py
ribotish/zbio/fa.py
ribotish/zbio/gtf.py
ribotish/zbio/interval.py
ribotish/zbio/io.py
ribotish/zbio/orf.py
ribotish/zbio/plot.py
ribotish/zbio/ribo.py
ribotish/zbio/stat.py
ribotish/zbio/tools.py
ribotish-0.2.8.data/scripts/ribotish
ribotish-0.2.8.dist-info/LICENSE
ribotish-0.2.8.dist-info/METADATA
ribotish-0.2.8.dist-info/WHEEL
ribotish-0.2.8.dist-info/top_level.txt
ribotish-0.2.8.dist-info/RECORD
