Metadata-Version: 2.1
Name: ribotish
Version: 0.2.8
Summary: Python Modules for Riboseq data analysis.
Home-page: https://github.com/zhpn1024/ribotish
Author: Peng Zhang
Author-email: zhpn1024@163.com
License: GNU General Public License (GPL)
Keywords: Python,Riboseq,translation
Platform: UNKNOWN
Classifier: Environment :: Console
Classifier: Development Status :: 4 - Beta
Classifier: Intended Audience :: Developers
Classifier: License :: OSI Approved :: GNU General Public License (GPL)
Classifier: License :: Free for non-commercial use
Classifier: Operating System :: Unix
Classifier: Programming Language :: Python :: 2.7
Classifier: Programming Language :: Python :: 3
Classifier: Topic :: Scientific/Engineering :: Bio-Informatics
Requires-Dist: pysam >=0.8.3
Requires-Dist: matplotlib >=1.4.3
Requires-Dist: scipy >=0.15.1
